dydx/__init__.py
dydx/core/__init__.py
dydx/core/__init__.pyi
dydx/core/exc.py
dydx/core/util.py
dydx/core/validation.py
dydx/core/http/__init__.py
dydx/core/http/__init__.pyi
dydx/core/http/client.py
dydx/core/types/__init__.py
dydx/core/types/__init__.pyi
dydx/core/types/enums.py
dydx/core/types/market.py
dydx/core/types/misc.py
dydx/core/types/order.py
dydx/core/types/positions.py
dydx/core/ws/__init__.py
dydx/core/ws/__init__.pyi
dydx/core/ws/base.py
dydx/core/ws/multiplex_rpc.py
dydx/core/ws/multiplex_streams_rpc.py
dydx/core/ws/serial_rpc.py
dydx/core/ws/streams_rpc.py
dydx/indexer/__init__.py
dydx/indexer/__init__.pyi
dydx/indexer/_indexer.py
dydx/indexer/data/__init__.py
dydx/indexer/data/__init__.pyi
dydx/indexer/data/_data.py
dydx/indexer/data/core.py
dydx/indexer/data/get_candles.py
dydx/indexer/data/get_fills.py
dydx/indexer/data/get_funding_payments.py
dydx/indexer/data/get_historical_funding.py
dydx/indexer/data/get_markets.py
dydx/indexer/data/get_order.py
dydx/indexer/data/get_order_book.py
dydx/indexer/data/get_subaccounts.py
dydx/indexer/data/get_trades.py
dydx/indexer/data/list_orders.py
dydx/indexer/data/list_positions.py
dydx/indexer/streams/__init__.py
dydx/indexer/streams/__init__.pyi
dydx/indexer/streams/_streams.py
dydx/indexer/streams/core.py
dydx/indexer/streams/subaccounts.py
dydx/node/__init__.py
dydx/node/__init__.pyi
dydx/node/private/__init__.py
dydx/node/private/__init__.pyi
dydx/node/private/_private.py
dydx/node/private/cancel_order.py
dydx/node/private/core.py
dydx/node/private/place_order.py
dydx/sdk/__init__.py
dydx/sdk/__init__.pyi
dydx/sdk/core/__init__.py
dydx/sdk/core/__init__.pyi
dydx/sdk/core/exc.py
dydx/sdk/core/mixins.py
dydx/sdk/core/naming.py
dydx/sdk/market/__init__.py
dydx/sdk/market/__init__.pyi
dydx/sdk/market/market_data/__init__.py
dydx/sdk/market/market_data/__init__.pyi
dydx/sdk/market/market_data/_market_data.py
dydx/sdk/market/market_data/candles.py
dydx/sdk/market/market_data/depth.py
dydx_trading_sdk-0.1.2.dist-info/METADATA
dydx_trading_sdk-0.1.2.dist-info/WHEEL
dydx_trading_sdk-0.1.2.dist-info/top_level.txt
dydx_trading_sdk-0.1.2.dist-info/RECORD
